aissociate/__init__.py
aissociate/client.py
aissociate/constants.py
aissociate/exceptions.py
aissociate/parser.py
aissociate/models/__init__.py
aissociate/models/events.py
aissociate/models/shared.py
aissociate-0.1.3.dist-info/LICENSE
aissociate-0.1.3.dist-info/METADATA
aissociate-0.1.3.dist-info/WHEEL
aissociate-0.1.3.dist-info/top_level.txt
aissociate-0.1.3.dist-info/RECORD
