Metadata-Version: 2.2
Name: aissociate
Version: 0.1.3
Summary: The official Python library for the AIssociate API.
Author-email: Christoph Sonntag <christoph.sonntag@aissociate.at>
Project-URL: Repository, https://gitlab.com/aissociate/aissociate-python
Project-URL: Homepage, https://aissociate.at
Classifier: Programming Language :: Python :: 3
Classifier: Operating System :: OS Independent
Classifier: Development Status :: 4 - Beta
Classifier: Intended Audience :: Developers
Classifier: Intended Audience :: Legal Industry
Classifier: Topic :: Software Development :: Libraries
Classifier: Topic :: Software Development :: Libraries :: Python Modules
Requires-Python: >=3.8
License-File: LICENSE
Requires-Dist: httpx<1,>=0.28.0
Requires-Dist: python-dotenv
